	{
 "namespace": "tabbed_upsell",

  "patch_notes_forestx": {
    "type": "stack_panel",
    "size": [ "100%", "100%c" ],
    "controls": [
      {
        "imagen_panel": {
          "type": "panel",
          "size": [ "100%", "100%c" ],
          "controls": [
            {
              "furni_imagen": {
                "type": "image",
                "size": [ 320, 200 ],
                "texture": "textures/button/update"
              }
            }
          ]
        }
      },
      {
        "patch_notes_text": {
          "type": "label",
          "color": "$body_text_color",
          "size": [ "100%-4px", "default" ],
          "text": "
Приветствуем вас в новой версии 3.2.0! В которую  мы добавили банановые джунгли и исправили очень неприятные ошибки.
Убедитесь, что вы используете §2самую новую версию§r нашего дополнения для того, чтобы убедиться в этом, проверьте наш GitHub по ссылке §9https://github.com/MagicalAlexey/Forest-X/releases§r. Если у вас возникли вопросы или есть интересные идеи, тогда вы можете сообщить нам в личных сообщениях группы ВК по ссылке §9vk.com/minefoxru§r.
§4Важно!§r Перед использованием дополения прочитайте лицензию MIT, которая находится в файлах нашего дополнения.
§lДополнительно§r
Творческий вклад сделан: @Cakeoo, @Sunway_Official и др.
Некоторый контент был портирован из модов Minecraft Java Edition

§lСписок изменений§r
§oБананы§r
- Добавлены банановые листья
- Добавлены бананы
- С банановых листьев можно собирать бананы
- Успевайте во время собирать урожай, иначе вы его можете потерять
§oБанановые джунгли§r
- Добавлена новая вариация джунглей - банановые джунгли
§oТигр§r
- Добавлен тигр
- Тигров можно размножить при помощи любого сырого вида мяса
- Тигры очень опасный и сильный хищник, который имеет 40 единиц жизни и силу урона 8, так что лучше не попадайтесь тиграм на глаза
- Добавлен спавн тигра в биом джунгли
§oЭкспериментальные функции§r
- Пакет с экспериментальными функциями распространяется отдельно от аддона
- Минимальная версия поддерживаемая пакетом - 1.17.30+
- Экспериментальные функции больше не имеют названия Forest X Plus
- Добавлена плотная паутина
- Добавлен чугунный забор
- Добавлены янтарные пещеры
- Пакет не доступен в релизной версии аддона
§oСовместимость§r
- Минимальная поддерживаемая версия игры теперь 1.17.30
- Добавлена поддержка версии 1.18.0 для будущих изменений
- Аддон пока временно не совместим с новой генерацией из 1.18 т.к. биомы из аддона не генерируются
§oИзменения§r
- Теперь в Фруктовом лесу деревья с фруктами
- Дикий цветок больше не появляется на равнинах
- Изменён крафт банки
- В пакет ресурсов добавлен субпакет с шрифтом из Java Minecraft
- Теперь экраном изменений используется файл update.png
- Удалена глубинная серная руда
§oИсправления§r
- Исправлена ошибка из-за которой мышь не появлялась в степи
- Исправлены ошибки в списке изменений 

",
          "font_type": "smooth",
          "bindings": [
            {
              "binding_name": "#patch_description",
              "binding_type": "global"
            },
            {
              "binding_type": "global",
              "binding_condition": "once",
              "binding_name": "#tts_dialog_body"
            }
          ],
          "property_bag": {
            "#tts_dialog_body": "#patch_description"
          }
        }
      }
    ]
 },
 "scroll@common.scrolling_panel": {
  "$show_background": false,
  "$scrolling_content": "tabbed_upsell.patch_notes_forestx"
 },
 "tabbed_upseel_screen_panel@common_dialogs.main_panel_no_buttons": {
  "size": ["100%" ,"100%" ],
  "$text_name": "Добро пожаловать в новую версию Forest X под номером 3.2.0!",
  "$child_control": "tabbed_upsell.scroll"
 }
}